CHANGES.rst
LICENSE
MANIFEST.in
README.rst
TODO.rst
setup.py
bin/bootstrap_goto.py
bin/goto.sh
goto/__init__.py
goto/configparser.py
goto/goto.py
goto/label.py
goto/storage.py
goto/test/__init__.py
goto_dir.egg-info/PKG-INFO
goto_dir.egg-info/SOURCES.txt
goto_dir.egg-info/dependency_links.txt
goto_dir.egg-info/top_level.txt