Metadata-Version: 1.1
Name: goto-dir
Version: 0.2.0
Summary: easy'n'fast cd'ing.
Home-page: https://github.com/pauloborges/goto
Author: Paulo Borges
Author-email: pauloborgesfilho@gmail.com
License: See LICENSE.
Platform: UNKNOWN
Classifier: Development Status :: 3 - Alpha
Classifier: Environment :: Console
Classifier: License :: OSI Approved :: GNU General Public License v3 (GPLv3)
Classifier: Natural Language :: English
Classifier: Programming Language :: Python :: 2.7
Classifier: Topic :: System :: Shells
Classifier: Intended Audience :: Developers
Classifier: Intended Audience :: End Users/Desktop
